masav/__init__.py
masav/payment.py
tests/__init__.py
tests/test_payment.py
masav-0.0.2.dist-info/LICENCE
masav-0.0.2.dist-info/METADATA
masav-0.0.2.dist-info/WHEEL
masav-0.0.2.dist-info/top_level.txt
masav-0.0.2.dist-info/RECORD
