Metadata-Version: 2.1
Name: masav
Version: 0.0.2
Summary: Python API for Israeli Masav payments
Home-page: https://github.com/omrirz/masav
Author: Omri Rozenzaft
Author-email: omrirz@gmail.com
License: UNKNOWN
Platform: UNKNOWN
Classifier: Programming Language :: Python :: 3
Classifier: License :: OSI Approved :: MIT License
Classifier: Operating System :: OS Independent
Requires-Python: >=3.6
